Metadata-Version: 1.2
Name: whazzap
Version: 0.1
Summary: A library to treat message text import without media from WhatsApp
Home-page: https://github.com/beatrizcastro89/whazzap
Author: Beatriz Yumi Simões de Castro
Author-email: beatrizyumi@gmail.com
License: MIT
Platform: UNKNOWN
Requires-Python: >=3.6
